{
  "semana": 2,
  "oponente": "A.Rod Gangs",
  "oponente_id": 3,
  "week_start": "2026-03-30",
  "week_end": "2026-04-05",
  "mis_bat": {
    "equipo": "Dando Tabla",
    "jugadores": 14,
    "HR_avg": 5.6,
    "OPS": 0.615,
    "wOBA": 0.293,
    "xwOBA": 0.281,
    "EV": 87.9,
    "Barrel%": 2.4
  },
  "opp_bat": {
    "equipo": "A.Rod Gangs",
    "jugadores": 12,
    "HR_avg": 7.5,
    "OPS": 0.878,
    "wOBA": 0.419,
    "xwOBA": 0.348,
    "EV": 91.7,
    "Barrel%": 15.5
  },
  "mis_pit": {
    "equipo": "Dando Tabla",
    "jugadores": 9,
    "ERA": 3.07,
    "xERA": 3.5,
    "Ks": 74.0,
    "xwOBA": 0.285,
    "EV_against": 88.0
  },
  "opp_pit": {
    "equipo": "A.Rod Gangs",
    "jugadores": 11,
    "ERA": 4.9,
    "xERA": 4.21,
    "Ks": 99.9,
    "xwOBA": 0.307,
    "EV_against": 89.5
  },
  "prob_ganar": 49.8,
  "prob_perder": 50.2,
  "odds_ganar": "+101",
  "odds_perder": "-101"
}